{
    "1": "Will Stafford",
    "2": "Ivan Di Liberti",
    "3": "Andrei Sipoș",
    "4": "Mateusz Łełyk",
    "5": "Paul-André Melliès",
    "6": "Joost Joosten",
    "7": "Gianluca Curzi",
    "8": "Andrew Brooke-Taylor",
    "9": "Valentin Goranko",
    "10": "Fedor Pakhomov",
    "11": "Alexis Saurin",
    "12": "Rasmus Blanck",
    "13": "Dominik Kirst",
    "14": "Luca San Mauro",
    "16": "Gianluca Curzi",
    "17": "Fredrik Engström",
    "18": "Takako Nemoto",
    "19": "Sebastian Enqvist",
    "21": "Ivan Di Liberti",
    "22": "Marianna Girlando"
}
